CHANGELOG.md
LICENSE
MANIFEST.in
README.md
setup.py
pybanner/__init__.py
pybanner/pybanner.py
pybanner.egg-info/PKG-INFO
pybanner.egg-info/SOURCES.txt
pybanner.egg-info/dependency_links.txt
pybanner.egg-info/not-zip-safe
pybanner.egg-info/top_level.txt